[
    {
        "id": 1,
        "name": "QP",
        "detail": "【強化資源】\n量子の欠片。\n多くの可能性を許容する霊子のゆらぎ。\n燃料として、さまざまな魔術に使われる。",
        "imageId": 5,
        "type": 1,
        "dropPriority": 9010
    },
    {
        "id": 2,
        "name": "聖晶石",
        "detail": "聖なる力の宿った石。\nあまたの未来を確定させる概念が結晶化したもの。\n疑似霊子結晶とも呼ばれる。",
        "imageId": 6,
        "type": 2,
        "dropPriority": 9001
    },
    {
        "id": 3,
        "name": "マナプリズム",
        "detail": "【交換アイテム】\nマナを濃縮して作られた結晶体。\nマナとは惑星上に満ちた魔力の総称。",
        "imageId": 7,
        "type": 5,
        "dropPriority": 9003
    },
    {
        "id": 4,
        "name": "フレンドポイント",
        "detail": "友情の証",
        "imageId": 12,
        "type": 13,
        "dropPriority": 9011
    },
    {
        "id": 5,
        "name": "クエストクリア報酬QP",
        "detail": "【強化資源】\n量子の欠片。\n多くの可能性を許容する霊子のゆらぎ。\n燃料として、さまざまな魔術に使われる。",
        "imageId": 5,
        "type": 16,
        "dropPriority": 9012
    },
    {
        "id": 6,
        "name": "聖晶石",
        "detail": "聖なる力の宿った石。\nあまたの未来を確定させる概念が結晶化したもの。\n疑似霊子結晶とも呼ばれる。",
        "imageId": 6,
        "type": 17,
        "dropPriority": 9001
    },
    {
        "id": 16,
        "name": "聖晶片",
        "detail": "聖晶石のかけら。\n複数集めれば聖晶石を造り上げることができる。",
        "imageId": 16,
        "type": 20,
        "dropPriority": 9002
    },
    {
        "id": 17,
        "name": "無記名霊基",
        "detail": "【特殊召喚アイテム】\n溢れ出た霊基の残滓。",
        "imageId": 17,
        "type": 21,
        "dropPriority": 9005
    },
    {
        "id": 18,
        "name": "レアプリズム",
        "detail": "【交換アイテム】\n特別な環境下でマナを濃縮することで産まれる\n希少なマナの結晶体。",
        "imageId": 18,
        "type": 22,
        "dropPriority": 9004
    },
    {
        "id": 99,
        "name": "？？？",
        "detail": "？？？",
        "imageId": 99,
        "type": 15,
        "dropPriority": 2099
    },
    {
        "id": 100,
        "name": "黄金の果実",
        "detail": "【AP回復アイテム】\nAPを100%分回復する。",
        "imageId": 100,
        "type": 3,
        "dropPriority": 9009
    },
    {
        "id": 101,
        "name": "白銀の果実",
        "detail": "【AP回復アイテム】\nAPを50%分回復する。",
        "imageId": 101,
        "type": 3,
        "dropPriority": 9008
    },
    {
        "id": 102,
        "name": "赤銅の果実",
        "detail": "【AP回復アイテム】\nAPを10回復する。",
        "imageId": 102,
        "type": 4,
        "dropPriority": 9007
    },
    {
        "id": 4001,
        "name": "呼符",
        "detail": "【霊基召喚アイテム】\n召喚を補助する道具。\n時代を超えて輝く道しるべ。",
        "imageId": 4001,
        "type": 9,
        "dropPriority": 9006
    },
    {
        "id": 6001,
        "name": "剣の輝石",
        "detail": "【スキル強化素材】\n剣士の力が宿った光輝く石",
        "imageId": 6001,
        "type": 11,
        "dropPriority": 8100
    },
    {
        "id": 6002,
        "name": "弓の輝石",
        "detail": "【スキル強化素材】\n弓兵の力が宿った光輝く石",
        "imageId": 6002,
        "type": 11,
        "dropPriority": 8099
    },
    {
        "id": 6003,
        "name": "槍の輝石",
        "detail": "【スキル強化素材】\n槍兵の力が宿った光輝く石",
        "imageId": 6003,
        "type": 11,
        "dropPriority": 8098
    },
    {
        "id": 6004,
        "name": "騎の輝石",
        "detail": "【スキル強化素材】\n騎士の力が宿った光輝く石",
        "imageId": 6004,
        "type": 11,
        "dropPriority": 8097
    },
    {
        "id": 6005,
        "name": "術の輝石",
        "detail": "【スキル強化素材】\n魔術師の力が宿った光輝く石",
        "imageId": 6005,
        "type": 11,
        "dropPriority": 8096
    },
    {
        "id": 6006,
        "name": "殺の輝石",
        "detail": "【スキル強化素材】\n暗殺者の力が宿った光輝く石",
        "imageId": 6006,
        "type": 11,
        "dropPriority": 8095
    },
    {
        "id": 6007,
        "name": "狂の輝石",
        "detail": "【スキル強化素材】\n狂戦士の力が宿った光輝く石",
        "imageId": 6007,
        "type": 11,
        "dropPriority": 8094
    },
    {
        "id": 6008,
        "name": "無の輝石",
        "detail": "【スキル強化素材】\n未知の力が宿った光輝く石",
        "imageId": 6008,
        "type": 11,
        "dropPriority": 8093
    },
    {
        "id": 6101,
        "name": "剣の魔石",
        "detail": "【スキル強化素材】\n剣士の強い力が宿った魔法石",
        "imageId": 6101,
        "type": 11,
        "dropPriority": 8200
    },
    {
        "id": 6102,
        "name": "弓の魔石",
        "detail": "【スキル強化素材】\n弓兵の強い力が宿った魔法石",
        "imageId": 6102,
        "type": 11,
        "dropPriority": 8199
    },
    {
        "id": 6103,
        "name": "槍の魔石",
        "detail": "【スキル強化素材】\n槍兵の強い力が宿った魔法石",
        "imageId": 6103,
        "type": 11,
        "dropPriority": 8198
    },
    {
        "id": 6104,
        "name": "騎の魔石",
        "detail": "【スキル強化素材】\n騎士の強い力が宿った魔法石",
        "imageId": 6104,
        "type": 11,
        "dropPriority": 8197
    },
    {
        "id": 6105,
        "name": "術の魔石",
        "detail": "【スキル強化素材】\n魔術師の強い力が宿った魔法石",
        "imageId": 6105,
        "type": 11,
        "dropPriority": 8196
    },
    {
        "id": 6106,
        "name": "殺の魔石",
        "detail": "【スキル強化素材】\n暗殺者の強い力が宿った魔法石",
        "imageId": 6106,
        "type": 11,
        "dropPriority": 8195
    },
    {
        "id": 6107,
        "name": "狂の魔石",
        "detail": "【スキル強化素材】\n狂戦士の強い力が宿った魔法石",
        "imageId": 6107,
        "type": 11,
        "dropPriority": 8194
    },
    {
        "id": 6108,
        "name": "無の魔石",
        "detail": "【スキル強化素材】\n未知の強い力が宿った魔法石",
        "imageId": 6108,
        "type": 11,
        "dropPriority": 8193
    },
    {
        "id": 6201,
        "name": "剣の秘石",
        "detail": "【スキル強化素材】\n剣士の強大な力が宿った宝石",
        "imageId": 6201,
        "type": 11,
        "dropPriority": 8300
    },
    {
        "id": 6202,
        "name": "弓の秘石",
        "detail": "【スキル強化素材】\n弓兵の強大な力が宿った宝石",
        "imageId": 6202,
        "type": 11,
        "dropPriority": 8299
    },
    {
        "id": 6203,
        "name": "槍の秘石",
        "detail": "【スキル強化素材】\n槍兵の強大な力が宿った宝石",
        "imageId": 6203,
        "type": 11,
        "dropPriority": 8298
    },
    {
        "id": 6204,
        "name": "騎の秘石",
        "detail": "【スキル強化素材】\n騎士の強大な力が宿った宝石",
        "imageId": 6204,
        "type": 11,
        "dropPriority": 8297
    },
    {
        "id": 6205,
        "name": "術の秘石",
        "detail": "【スキル強化素材】\n魔術師の強大な力が宿った宝石",
        "imageId": 6205,
        "type": 11,
        "dropPriority": 8296
    },
    {
        "id": 6206,
        "name": "殺の秘石",
        "detail": "【スキル強化素材】\n暗殺者の強大な力が宿った宝石",
        "imageId": 6206,
        "type": 11,
        "dropPriority": 8295
    },
    {
        "id": 6207,
        "name": "狂の秘石",
        "detail": "【スキル強化素材】\n狂戦士の強大な力が宿った宝石",
        "imageId": 6207,
        "type": 11,
        "dropPriority": 8294
    },
    {
        "id": 6208,
        "name": "無の秘石",
        "detail": "【スキル強化素材】\n未知の強大な力が宿った宝石",
        "imageId": 6208,
        "type": 11,
        "dropPriority": 8293
    },
    {
        "id": 6501,
        "name": "鳳凰の羽根",
        "detail": "【スキル強化＆霊基再臨素材】\n東洋の霊鳥の羽根",
        "imageId": 6501,
        "type": 11,
        "dropPriority": 8196
    },
    {
        "id": 6502,
        "name": "世界樹の種",
        "detail": "【スキル強化＆霊基再臨素材】\n世界を体現する巨木の種",
        "imageId": 6502,
        "type": 11,
        "dropPriority": 8200
    },
    {
        "id": 6503,
        "name": "英雄の証",
        "detail": "【スキル強化＆霊基再臨素材】\n英雄と認められた証。\n多くの人々が持つが、\n自覚していないため忘れられる。",
        "imageId": 6503,
        "type": 11,
        "dropPriority": 8100
    },
    {
        "id": 6504,
        "name": "星の欠片",
        "detail": "",
        "imageId": 6504,
        "type": 11,
        "dropPriority": 8191
    },
    {
        "id": 6505,
        "name": "虚影の塵",
        "detail": "【スキル強化＆霊基再臨素材】\n虚ろな影が消える時に飛び散る塵",
        "imageId": 6505,
        "type": 11,
        "dropPriority": 8097
    },
    {
        "id": 6506,
        "name": "竜の逆鱗",
        "detail": "【スキル強化＆霊基再臨素材】\n竜種の顎の下に逆さについた鱗",
        "imageId": 6506,
        "type": 11,
        "dropPriority": 8298
    },
    {
        "id": 6507,
        "name": "混沌の爪",
        "detail": "【スキル強化＆霊基再臨素材】\nこの爪で傷をつけられた者は混沌の虜となる",
        "imageId": 6507,
        "type": 11,
        "dropPriority": 8300
    },
    {
        "id": 6508,
        "name": "ゴーストランタン",
        "detail": "【スキル強化＆霊基再臨素材】\n魂を油にして燃えるランタン",
        "imageId": 6508,
        "type": 11,
        "dropPriority": 8199
    },
    {
        "id": 6509,
        "name": "蛇の宝玉",
        "detail": "【スキル強化＆霊基再臨素材】\n蛇の瞳に睨まれているかのような宝玉",
        "imageId": 6509,
        "type": 11,
        "dropPriority": 8197
    },
    {
        "id": 6510,
        "name": "無間の歯車",
        "detail": "【スキル強化＆霊基再臨素材】\n永久機関の夢。\n一度回転しだすといつまでも回転し続ける歯車。",
        "imageId": 6510,
        "type": 11,
        "dropPriority": 8195
    },
    {
        "id": 6511,
        "name": "禁断の頁",
        "detail": "【スキル強化＆霊基再臨素材】\n何人も読んではならない頁。\nたいていは最初か最後にまぎれている。",
        "imageId": 6511,
        "type": 11,
        "dropPriority": 8194
    },
    {
        "id": 6512,
        "name": "竜の牙",
        "detail": "【スキル強化＆霊基再臨素材】\n竜種の牙。竜牙兵はこの牙を使って作られる。",
        "imageId": 6512,
        "type": 11,
        "dropPriority": 8098
    },
    {
        "id": 6513,
        "name": "隕蹄鉄",
        "detail": "【スキル強化＆霊基再臨素材】\n隕鉄で作られた強靭な蹄鉄。\n構成原子は同じであろうと、地球上で\n作られたものではないため特別な役割を持つ。",
        "imageId": 6513,
        "type": 11,
        "dropPriority": 8192
    },
    {
        "id": 6514,
        "name": "ホムンクルスベビー",
        "detail": "【スキル強化＆霊基再臨素材】\n魂を書き込む前のホムンクルスの幼体",
        "imageId": 6514,
        "type": 11,
        "dropPriority": 8193
    },
    {
        "id": 6515,
        "name": "八連双晶",
        "detail": "【スキル強化＆霊基再臨素材】\nゴーレムの体内で造られる多結晶体",
        "imageId": 6515,
        "type": 11,
        "dropPriority": 8198
    },
    {
        "id": 6516,
        "name": "凶骨",
        "detail": "【スキル強化＆霊基再臨素材】\n呪いを纏った禍々しい骨",
        "imageId": 6516,
        "type": 11,
        "dropPriority": 8099
    },
    {
        "id": 6517,
        "name": "蛮神の心臓",
        "detail": "【スキル強化＆霊基再臨素材】\n荒ぶるデミゴッドの心臓。\n偽りとはいえ神は神。\nその鼓動は多くの呪いを放つ。",
        "imageId": 6517,
        "type": 11,
        "dropPriority": 8299
    },
    {
        "id": 6518,
        "name": "精霊根",
        "detail": "【スキル強化＆霊基再臨素材】\n土の精霊の宿った根。\nこの根を石像に植え付けると、\nたちまち生きているかのように動き始めると云う。",
        "imageId": 6518,
        "type": 11,
        "dropPriority": 8297
    },
    {
        "id": 6519,
        "name": "戦馬の幼角",
        "detail": "【スキル強化＆霊基再臨素材】\n二角獣の頭毛の中に、\n隠れるように生えている小さな角。\n巨大な角が折れた際には、\nこの角がすぐさま成長して新たな角となるらしい。",
        "imageId": 6519,
        "type": 11,
        "dropPriority": 8296
    },
    {
        "id": 6520,
        "name": "血の涙石",
        "detail": "【スキル強化＆霊基再臨素材】\n巨大な目玉の怪物が息絶える瞬間に流す涙の結晶体。\n強烈な呪いが込められている。",
        "imageId": 6520,
        "type": 11,
        "dropPriority": 8295
    },
    {
        "id": 6521,
        "name": "黒獣脂",
        "detail": "【スキル強化＆霊基再臨素材】\n魂を喰らう獣の体表から採れるドロドロとした脂。\n蒸留により精製を幾度も繰り返すことで、\n上質の魔術資源となる。",
        "imageId": 6521,
        "type": 11,
        "dropPriority": 8294
    },
    {
        "id": 6522,
        "name": "愚者の鎖",
        "detail": "【スキル強化＆霊基再臨素材】\n天に召されゆく儚き魂を\n現世に繋ぎ留めようとして造られた鎖。",
        "imageId": 6522,
        "type": 11,
        "dropPriority": 8096
    },
    {
        "id": 6523,
        "name": "封魔のランプ",
        "detail": "【スキル強化＆霊基再臨素材】\n強大な魔力を持つ精霊が\n封じこめられているという妖艶なランプ。",
        "imageId": 6523,
        "type": 11,
        "dropPriority": 8293
    },
    {
        "id": 6524,
        "name": "大騎士勲章",
        "detail": "【スキル強化＆霊基再臨素材】\n廉潔なる騎士の忠義と勲功を讃える勲章。",
        "imageId": 6524,
        "type": 11,
        "dropPriority": 8190
    },
    {
        "id": 6525,
        "name": "智慧のスカラベ",
        "detail": "【スキル強化＆霊基再臨素材】\n再生と復活の象徴たる聖なる虫の飾り物。\n難題を解きし真に聡しき者にのみ与えられる。",
        "imageId": 6525,
        "type": 11,
        "dropPriority": 8292
    },
    {
        "id": 6526,
        "name": "追憶の貝殻",
        "detail": "【スキル強化＆霊基再臨素材】\n悠久の時を生きた貝の殻。\n殻口に耳を当てると、遥か太古の\n清らかな潮騒が聞こえてくる。",
        "imageId": 6526,
        "type": 11,
        "dropPriority": 8189
    },
    {
        "id": 6999,
        "name": "伝承結晶",
        "detail": "【スキル強化＆霊基再臨素材】\n人類史とマナの奔流が交差する事で\n産み出される高純度の魔力結晶。\n物質化した英霊の素材とも言える。",
        "imageId": 6999,
        "type": 11,
        "dropPriority": 8900
    },
    {
        "id": 7001,
        "name": "セイバーピース",
        "detail": "【霊基再臨素材】\nセイバークラスを象徴するピース",
        "imageId": 7001,
        "type": 12,
        "dropPriority": 5200
    },
    {
        "id": 7002,
        "name": "アーチャーピース",
        "detail": "【霊基再臨素材】\nアーチャークラスを象徴するピース",
        "imageId": 7002,
        "type": 12,
        "dropPriority": 5199
    },
    {
        "id": 7003,
        "name": "ランサーピース",
        "detail": "【霊基再臨素材】\nランサークラスを象徴するピース",
        "imageId": 7003,
        "type": 12,
        "dropPriority": 5198
    },
    {
        "id": 7004,
        "name": "ライダーピース",
        "detail": "【霊基再臨素材】\nライダークラスを象徴するピース",
        "imageId": 7004,
        "type": 12,
        "dropPriority": 5197
    },
    {
        "id": 7005,
        "name": "キャスターピース",
        "detail": "【霊基再臨素材】\nキャスタークラスを象徴するピース",
        "imageId": 7005,
        "type": 12,
        "dropPriority": 5196
    },
    {
        "id": 7006,
        "name": "アサシンピース",
        "detail": "【霊基再臨素材】\nアサシンクラスを象徴するピース",
        "imageId": 7006,
        "type": 12,
        "dropPriority": 5195
    },
    {
        "id": 7007,
        "name": "バーサーカーピース",
        "detail": "【霊基再臨素材】\nバーサーカークラスを象徴するピース",
        "imageId": 7007,
        "type": 12,
        "dropPriority": 5194
    },
    {
        "id": 7008,
        "name": "エクストラピース",
        "detail": "【霊基再臨素材】\nエクストラクラスを象徴するピース",
        "imageId": 7008,
        "type": 12,
        "dropPriority": 5193
    },
    {
        "id": 7101,
        "name": "セイバーモニュメント",
        "detail": "【霊基再臨素材】\nセイバークラスを称えるモニュメント",
        "imageId": 7101,
        "type": 12,
        "dropPriority": 5300
    },
    {
        "id": 7102,
        "name": "アーチャーモニュメント",
        "detail": "【霊基再臨素材】\nアーチャークラスを称えるモニュメント",
        "imageId": 7102,
        "type": 12,
        "dropPriority": 5299
    },
    {
        "id": 7103,
        "name": "ランサーモニュメント",
        "detail": "【霊基再臨素材】\nランサークラスを称えるモニュメント",
        "imageId": 7103,
        "type": 12,
        "dropPriority": 5298
    },
    {
        "id": 7104,
        "name": "ライダーモニュメント",
        "detail": "【霊基再臨素材】\nライダークラスを称えるモニュメント",
        "imageId": 7104,
        "type": 12,
        "dropPriority": 5297
    },
    {
        "id": 7105,
        "name": "キャスターモニュメント",
        "detail": "【霊基再臨素材】\nキャスタークラスを称えるモニュメント",
        "imageId": 7105,
        "type": 12,
        "dropPriority": 5296
    },
    {
        "id": 7106,
        "name": "アサシンモニュメント",
        "detail": "【霊基再臨素材】\nアサシンクラスを称えるモニュメント",
        "imageId": 7106,
        "type": 12,
        "dropPriority": 5295
    },
    {
        "id": 7107,
        "name": "バーサーカーモニュメント",
        "detail": "【霊基再臨素材】\nバーサーカークラスを称えるモニュメント",
        "imageId": 7107,
        "type": 12,
        "dropPriority": 5294
    },
    {
        "id": 7108,
        "name": "エクストラモニュメント",
        "detail": "【霊基再臨素材】\nエクストラクラスを称えるモニュメント",
        "imageId": 7108,
        "type": 12,
        "dropPriority": 5293
    },
    {
        "id": 7999,
        "name": "聖杯",
        "detail": "あらゆる願いを叶えるという器。\n形而上のものを汲み上げ、\n物質に転換する第三魔法の産物。",
        "imageId": 7999,
        "type": 12,
        "dropPriority": 5500
    },
    {
        "id": 94000301,
        "name": "ネロメダル〔銅〕",
        "detail": "【イベントアイテム】\n『ネロ祭』で褒章として与えられる銅のメダル",
        "imageId": 94000301,
        "type": 15,
        "dropPriority": 2001
    },
    {
        "id": 94000302,
        "name": "ネロメダル〔銀〕",
        "detail": "【イベントアイテム】\n『ネロ祭』で褒章として与えられる銀のメダル",
        "imageId": 94000302,
        "type": 15,
        "dropPriority": 2002
    },
    {
        "id": 94000303,
        "name": "ネロメダル〔金〕",
        "detail": "【イベントアイテム】\n『ネロ祭』で褒章として与えられる金のメダル",
        "imageId": 94000303,
        "type": 15,
        "dropPriority": 2003
    },
    {
        "id": 94000401,
        "name": "月見団子",
        "detail": "【イベントアイテム】\n『月の女神はお団子の夢を見るか？』で回収した、\n祭儀用の団子。",
        "imageId": 94000401,
        "type": 15,
        "dropPriority": 2001
    },
    {
        "id": 94000402,
        "name": "特選団子",
        "detail": "【イベントアイテム】\n『月の女神はお団子の夢を見るか？』で回収した、\n幻のニホンの銘菓、七や橋屋の特選団子。",
        "imageId": 94000402,
        "type": 15,
        "dropPriority": 2002
    },
    {
        "id": 94000501,
        "name": "プチケーキ",
        "detail": "【イベントアイテム】\n『歌うカボチャ城の冒険』で手に入れた\nちいさなカップケーキ。",
        "imageId": 94000501,
        "type": 15,
        "dropPriority": 2001
    },
    {
        "id": 94000502,
        "name": "スイートキャンドル",
        "detail": "【イベントアイテム】\n『歌うカボチャ城の冒険』で手に入れた\n艶やかな光を放つキャンドル。",
        "imageId": 94000502,
        "type": 15,
        "dropPriority": 2002
    },
    {
        "id": 94000503,
        "name": "いたずらコウモリ",
        "detail": "【イベントアイテム】\n『歌うカボチャ城の冒険』で手に入れた\nかわいいコウモリの飾りもの。",
        "imageId": 94000503,
        "type": 15,
        "dropPriority": 2003
    },
    {
        "id": 94000504,
        "name": "かぼちゃランタン",
        "detail": "【イベントアイテム】\n『歌うカボチャ城の冒険』で手に入れた\nとぼけたカボチャの置きもの。",
        "imageId": 94000504,
        "type": 15,
        "dropPriority": 2004
    },
    {
        "id": 94000505,
        "name": "ティンクルキャンディ",
        "detail": "【イベントアイテム／霊基再臨素材】\n『歌うカボチャ城の冒険』で手に入れた\nアイドルスターにぴったりなキュートなキャンディ。",
        "imageId": 94000505,
        "type": 15,
        "dropPriority": 2005
    },
    {
        "id": 94000901,
        "name": "九十九髪茄子",
        "detail": "【イベントアイテム】\n『ぐだぐだ本能寺』で手に入れた\n天下三茄子と称えられる茶入……らしきモノじゃ。",
        "imageId": 94000901,
        "type": 15,
        "dropPriority": 2001
    },
    {
        "id": 94000902,
        "name": "曜変天目茶碗",
        "detail": "【イベントアイテム】\n『ぐだぐだ本能寺』で手に入れた\n最上級の天目茶碗……らしきモノじゃな。",
        "imageId": 94000902,
        "type": 15,
        "dropPriority": 2002
    },
    {
        "id": 94000903,
        "name": "平蜘蛛",
        "detail": "【イベントアイテム】\n『ぐだぐだ本能寺』で手に入れた\n平蜘蛛の茶釜……らしきモノじゃぞ。",
        "imageId": 94000903,
        "type": 15,
        "dropPriority": 2003
    },
    {
        "id": 94000904,
        "name": "本能寺ポイント",
        "detail": "【イベントポイント】\n『ぐだぐだ本能寺』で手に入れた\nイベントポイント、で、あるか！",
        "imageId": 94000904,
        "type": 14,
        "dropPriority": 3004
    },
    {
        "id": 94000905,
        "name": "黄金髑髏",
        "detail": "【イベントアイテム／霊基再臨素材】\n『ぐだぐだ本能寺』で手に入れた\nカッコいい金の髑髏アクセサリーなのじゃ！",
        "imageId": 94000905,
        "type": 15,
        "dropPriority": 2005
    },
    {
        "id": 94001201,
        "name": "ミニリボン",
        "detail": "【イベントアイテム】\n『ほぼ週間サンタオルタさん』で手に入れた\nクリスマスツリーを彩るかわいいリボン。",
        "imageId": 94001201,
        "type": 15,
        "dropPriority": 2001
    },
    {
        "id": 94001202,
        "name": "シルバーベル",
        "detail": "【イベントアイテム】\n『ほぼ週間サンタオルタさん』で手に入れた\nクリスマスツリーに吊るす聖なるベル。",
        "imageId": 94001202,
        "type": 15,
        "dropPriority": 2002
    },
    {
        "id": 94001203,
        "name": "ゴールドスター",
        "detail": "【イベントアイテム】\n『ほぼ週間サンタオルタさん』で手に入れた\nクリスマスツリーのてっぺんに輝く星。",
        "imageId": 94001203,
        "type": 15,
        "dropPriority": 2003
    },
    {
        "id": 94001204,
        "name": "魔法のくつした",
        "detail": "【イベントアイテム】\n『ほぼ週間サンタオルタさん』で手に入れた\nこどもたちの願いの詰まったくつした。",
        "imageId": 94001204,
        "type": 15,
        "dropPriority": 2004
    },
    {
        "id": 94001205,
        "name": "樽入りチキン",
        "detail": "【イベントアイテム／霊基再臨素材】\n『ほぼ週間 サンタオルタさん』で手に入れた\nクリスマスパーティーに欠かせない山盛りのチキン。",
        "imageId": 94001205,
        "type": 15,
        "dropPriority": 2005
    },
    {
        "id": 94001206,
        "name": "特別引換券",
        "detail": "【イベントアイテム】\n『ほぼ週間サンタオルタさん』で\nごほうびとして与えられる謎のチケット。",
        "imageId": 94001206,
        "type": 15,
        "dropPriority": 2006
    },
    {
        "id": 94001501,
        "name": "シンクウカーン",
        "detail": "【イベントアイテム】\n 『セイバーウォーズ』で手に入れた機械部品。\n 何かに使うらしいが何に使うかは永遠の謎。",
        "imageId": 94001501,
        "type": 15,
        "dropPriority": 2003
    },
    {
        "id": 94001502,
        "name": "バンノウレンズ",
        "detail": "【イベントアイテム】\n 『セイバーウォーズ』で手に入れた機械部品。\n Ａ粒子を観測、収束させるレンズ。\n ワープとかに使う。",
        "imageId": 94001502,
        "type": 15,
        "dropPriority": 2002
    },
    {
        "id": 94001503,
        "name": "トランＧスター",
        "detail": "【イベントアイテム】\n 『セイバーウォーズ』で手に入れた機械部品。\n 信号変換器であり、シンプルだが大事。\n よく市場とかで売ってる。",
        "imageId": 94001503,
        "type": 15,
        "dropPriority": 2001
    },
    {
        "id": 94001504,
        "name": "アルトリウム",
        "detail": "【イベントポイント】\n 『セイバーウォーズ』で手に入れた謎の素材。\n 超高密度のエネルギー結晶。キラキラ光る。\n 約束されたヒロインの証、とも言われている。",
        "imageId": 94001504,
        "type": 14,
        "dropPriority": 3004
    },
    {
        "id": 94001801,
        "name": "マシュからの手紙",
        "detail": "【イベントアイテム】\n『チョコレート・レディの空騒ぎ』で\nマシュから届いた何の変哲もない手紙。",
        "imageId": 94001801,
        "type": 15,
        "dropPriority": 2001
    },
    {
        "id": 94001802,
        "name": "材料チョコ",
        "detail": "【イベントアイテム】\n『チョコレート・レディの空騒ぎ』で手に入れた\nシンプルなチョコレート。",
        "imageId": 94001802,
        "type": 15,
        "dropPriority": 2002
    },
    {
        "id": 94001803,
        "name": "剣のコインチョコ",
        "detail": "【イベントアイテム】\n『チョコレート・レディの空騒ぎ』で手に入れた\nセイバーのエンブレムが刻まれた\nコイン型のチョコ。",
        "imageId": 94001803,
        "type": 15,
        "dropPriority": 2010
    },
    {
        "id": 94001804,
        "name": "弓のコインチョコ",
        "detail": "【イベントアイテム】\n『チョコレート・レディの空騒ぎ』で手に入れた\nアーチャーのエンブレムが刻まれた\nコイン型のチョコ。",
        "imageId": 94001804,
        "type": 15,
        "dropPriority": 2009
    },
    {
        "id": 94001805,
        "name": "槍のコインチョコ",
        "detail": "【イベントアイテム】\n『チョコレート・レディの空騒ぎ』で手に入れた\nランサーのエンブレムが刻まれた\nコイン型のチョコ。",
        "imageId": 94001805,
        "type": 15,
        "dropPriority": 2008
    },
    {
        "id": 94001806,
        "name": "騎のコインチョコ",
        "detail": "【イベントアイテム】\n『チョコレート・レディの空騒ぎ』で手に入れた\nライダーのエンブレムが刻まれた\nコイン型のチョコ。",
        "imageId": 94001806,
        "type": 15,
        "dropPriority": 2007
    },
    {
        "id": 94001807,
        "name": "術のコインチョコ",
        "detail": "【イベントアイテム】\n『チョコレート・レディの空騒ぎ』で手に入れた\nキャスターのエンブレムが刻まれた\nコイン型のチョコ。",
        "imageId": 94001807,
        "type": 15,
        "dropPriority": 2006
    },
    {
        "id": 94001808,
        "name": "殺のコインチョコ",
        "detail": "【イベントアイテム】\n『チョコレート・レディの空騒ぎ』で手に入れた\nアサシンのエンブレムが刻まれた\nコイン型のチョコ。",
        "imageId": 94001808,
        "type": 15,
        "dropPriority": 2005
    },
    {
        "id": 94001809,
        "name": "狂のコインチョコ",
        "detail": "【イベントアイテム】\n『チョコレート・レディの空騒ぎ』で手に入れた\nバーサーカーのエンブレムが刻まれた\nコイン型のチョコ。",
        "imageId": 94001809,
        "type": 15,
        "dropPriority": 2004
    },
    {
        "id": 94001810,
        "name": "全のコインチョコ",
        "detail": "【イベントアイテム】\n『チョコレート・レディの空騒ぎ』で手に入れた\nあらゆるクラスのコインチョコに交換可能な\nコイン型のチョコ。",
        "imageId": 94001810,
        "type": 15,
        "dropPriority": 2003
    },
    {
        "id": 94002001,
        "name": "隠されていた鍵",
        "detail": "【イベントアイテム】\n『空の境界/the Garden of Order』で手に入れた\n扉の鍵。存在しない筈の扉を開く。",
        "imageId": 94002001,
        "type": 15,
        "dropPriority": 2001
    },
    {
        "id": 94002002,
        "name": "黒猫フィギュア",
        "detail": "【イベントアイテム】\n『空の境界/the Garden of Order』で手に入れた\n黒猫を模したキュートなフィギュア。\n猫は舐めるものではない。舐められるものだ。",
        "imageId": 94002002,
        "type": 15,
        "dropPriority": 2004
    },
    {
        "id": 94002003,
        "name": "ストロベリーアイス",
        "detail": "【イベントアイテム】\n『空の境界/the Garden of Order』で手に入れた\nいかにも高級そうなイチゴ味のアイス。\n真夏の夜のお供に。",
        "imageId": 94002003,
        "type": 15,
        "dropPriority": 2003
    },
    {
        "id": 94002004,
        "name": "ミネラルウォーター",
        "detail": "【イベントアイテム】\n『空の境界/the Garden of Order』で手に入れた\n天然加工水。体の内側から美しく。\n……内側からとか、ちょっと怖い。",
        "imageId": 94002004,
        "type": 15,
        "dropPriority": 2002
    },
    {
        "id": 94002005,
        "name": "業物ナイフ",
        "detail": "【イベントアイテム／霊基再臨素材】\n『空の境界/the Garden of Order』で手に入れた\n熟練工の手によって作られたナイフ。\nたいてい、これをあげると機嫌は直る。",
        "imageId": 94002005,
        "type": 15,
        "dropPriority": 2005
    },
    {
        "id": 94002301,
        "name": "CBC2016特別招待状",
        "detail": "【イベント交換アイテム】\n『カルデアボーイズコレクション2016』で\n届けられた招待状。\nダ・ヴィンチ工房にて\n素敵なサプライズが貴方を待っています！",
        "imageId": 94002301,
        "type": 15,
        "dropPriority": 2001
    },
    {
        "id": 94002801,
        "name": "モナ・リザ（偽）",
        "detail": "【イベントアイテム】\n『ダ・ヴィンチと七人の贋作英霊』で\n手に入れた贋作品。\nダ・ヴィンチが描いたとされる貴婦人の絵。\n本物とは少し違うが、これはこれで美しい。",
        "imageId": 94002801,
        "type": 15,
        "dropPriority": 2003
    },
    {
        "id": 94002802,
        "name": "自画像（偽）",
        "detail": "【イベントアイテム】\n『ダ・ヴィンチと七人の贋作英霊』で\n手に入れた贋作品。\nダ・ヴィンチが描いたとされる自画像。\n本人とは似ても似つかない。",
        "imageId": 94002802,
        "type": 15,
        "dropPriority": 2002
    },
    {
        "id": 94002803,
        "name": "人体図（偽）",
        "detail": "【イベントアイテム】\n『ダ・ヴィンチと七人の贋作英霊』で\n手に入れた贋作品。\nダ・ヴィンチが描いたとされる人体図。\nデフォルメされている。",
        "imageId": 94002803,
        "type": 15,
        "dropPriority": 2001
    },
    {
        "id": 94002804,
        "name": "手稿（真）",
        "detail": "【イベントアイテム】\n『ダ・ヴィンチと七人の贋作英霊』で\n手に入れた手稿。\n万能人の頭脳が生み出した\n数多の閃きが記述されている。",
        "imageId": 94002804,
        "type": 15,
        "dropPriority": 2005
    },
    {
        "id": 94002805,
        "name": "手稿（偽）",
        "detail": "【イベントアイテム】\n『ダ・ヴィンチと七人の贋作英霊』で\n手に入れた手稿。\nいかにも暗号めいた\n荒唐無稽な内容が記述されている。",
        "imageId": 94002805,
        "type": 15,
        "dropPriority": 2004
    },
    {
        "id": 94003101,
        "name": "剣の印章",
        "detail": "【イベントアイテム】\n『Fate/Accel Zero Order』で手に入れた\nセイバーのエンブレムが刻まれた印章。",
        "imageId": 94003101,
        "type": 15,
        "dropPriority": 2007
    },
    {
        "id": 94003102,
        "name": "弓の印章",
        "detail": "【イベントアイテム】\n『Fate/Accel Zero Order』で手に入れた\nアーチャーのエンブレムが刻まれた印章。",
        "imageId": 94003102,
        "type": 15,
        "dropPriority": 2006
    },
    {
        "id": 94003103,
        "name": "槍の印章",
        "detail": "【イベントアイテム】\n『Fate/Accel Zero Order』で手に入れた\nランサーのエンブレムが刻まれた印章。",
        "imageId": 94003103,
        "type": 15,
        "dropPriority": 2005
    },
    {
        "id": 94003104,
        "name": "騎の印章",
        "detail": "【イベントアイテム】\n『Fate/Accel Zero Order』で手に入れた\nライダーのエンブレムが刻まれた印章。",
        "imageId": 94003104,
        "type": 15,
        "dropPriority": 2004
    },
    {
        "id": 94003105,
        "name": "術の印章",
        "detail": "【イベントアイテム】\n『Fate/Accel Zero Order』で手に入れた\nキャスターのエンブレムが刻まれた印章。",
        "imageId": 94003105,
        "type": 15,
        "dropPriority": 2003
    },
    {
        "id": 94003106,
        "name": "殺の印章",
        "detail": "【イベントアイテム】\n『Fate/Accel Zero Order』で手に入れた\nアサシンのエンブレムが刻まれた印章。",
        "imageId": 94003106,
        "type": 15,
        "dropPriority": 2002
    },
    {
        "id": 94003107,
        "name": "狂の印章",
        "detail": "【イベントアイテム】\n『Fate/Accel Zero Order』で手に入れた\nバーサーカーのエンブレムが刻まれた印章。",
        "imageId": 94003107,
        "type": 15,
        "dropPriority": 2001
    },
    {
        "id": 94003108,
        "name": "暗殺者の仮面",
        "detail": "【イベントアイテム／クエスト解放キー】\n『Fate/Accel Zero Order』で手に入れた\n暗殺者がつけていた仮面。",
        "imageId": 94003108,
        "type": 15,
        "dropPriority": 2008
    },
    {
        "id": 94003109,
        "name": "海魔の足",
        "detail": "【イベントアイテム／クエスト解放キー】\n『Fate/Accel Zero Order』で手に入れた\n名状しがたき魔物の足。",
        "imageId": 94003109,
        "type": 15,
        "dropPriority": 2009
    },
    {
        "id": 94003110,
        "name": "魔術鉱石の欠片",
        "detail": "【イベントアイテム／クエスト解放キー】\n『Fate/Accel Zero Order』で手に入れた\n魔力が込められた宝石の欠片。",
        "imageId": 94003110,
        "type": 15,
        "dropPriority": 2010
    },
    {
        "id": 94003111,
        "name": "至宝の杯",
        "detail": "【イベントアイテム／クエスト解放キー】\n『Fate/Accel Zero Order』で手に入れた\nとある王の財宝の一つである黄金の杯。",
        "imageId": 94003111,
        "type": 15,
        "dropPriority": 2011
    },
    {
        "id": 94003112,
        "name": "水晶球",
        "detail": "【イベントアイテム／霊基再臨素材】\n『Fate/Accel Zero Order』で手に入れた\n清廉な輝きを放つ水晶の玉。",
        "imageId": 94003112,
        "type": 15,
        "dropPriority": 2012
    },
    {
        "id": 94003701,
        "name": "ゴールデンおにぎり",
        "detail": "【イベントBP回復アイテム】\n『鬼哭酔夢魔京 羅生門』で手に入れた\n真にゴールデンな者に相応しいゴールデンな\nおにぎり。カレー味。甘口。\n腰が光ったり笹のような錦だったり房が\n乙女だったりもする。どれだ。\n鬼哭討伐戦においてBPを6回復する。",
        "imageId": 94003701,
        "type": 18,
        "dropPriority": 94012701
    },
    {
        "id": 94003702,
        "name": "鬼瓢箪",
        "detail": "【イベントアイテム】\n『鬼哭酔夢魔京 羅生門』で手に入れた\n人心を惑わす妖酒が入っている瓢箪。\n飲んだ者の「秘めた願望を促進させる」効能がある。\nなによりお酒として美味い。",
        "imageId": 94003702,
        "type": 15,
        "dropPriority": 2002
    },
    {
        "id": 94003703,
        "name": "ちからのおにぎり",
        "detail": "【イベントBP回復アイテム】\n『鬼哭酔夢魔京 羅生門』で手に入れた\n足柄山野の動物たちとの友情を育んだおにぎり。\n一口食べれば体の底から力が湧き溢れてくる。\n「やる気がもりもり湧いてくるわい！」\nとは通りすがりのライダーの評。\n鬼哭討伐戦においてBPを1回復する。",
        "imageId": 94003703,
        "type": 18,
        "dropPriority": 94012703
    },
    {
        "id": 94003901,
        "name": "金丹",
        "detail": "【イベントアイテム】\n『星の三蔵ちゃん、天竺に行く』で手に入れた\n飲めば不老不死になると言われている丹薬。\n\n「ええ、そんな美味い話はなかったわ！」",
        "imageId": 94003901,
        "type": 15,
        "dropPriority": 2003
    },
    {
        "id": 94003902,
        "name": "仙桃",
        "detail": "【イベントアイテム】\n『星の三蔵ちゃん、天竺に行く』で手に入れた\n仙界の園に実ると謳われる桃。\n\n「悟空はあの後お腹壊したんだって。\n何事も食べ過ぎは良くないって事ね！」",
        "imageId": 94003902,
        "type": 15,
        "dropPriority": 2002
    },
    {
        "id": 94003903,
        "name": "肉まん",
        "detail": "【イベントアイテム】\n『星の三蔵ちゃん、天竺に行く』で手に入れた\nボリュームたっぷりの肉まん。\nあつあつのうちに頬張りたい。\n\n「僕の大好物ブヒ。\n三口でたいてい飽きるのが玉に瑕ブヒ」",
        "imageId": 94003903,
        "type": 15,
        "dropPriority": 2001
    },
    {
        "id": 94003904,
        "name": "功徳の札",
        "detail": "【イベントアイテム／クエスト実行アイテム】\n『星の三蔵ちゃん、天竺に行く』で手に入れた\n修行者に救いをもたらすありがたい御札。\n\n「困ったらこれを売って路銀に換えていたわ！」",
        "imageId": 94003904,
        "type": 15,
        "dropPriority": 2004
    },
    {
        "id": 94003905,
        "name": "大蓮華",
        "detail": "【イベントアイテム】\n『星の三蔵ちゃん、天竺に行く』で手に入れた\n仏の瞳のごとき清廉な青さを湛えた蓮の花。\n\n「泥中にこそ美しく咲く……その在り方、\n武術の神髄に似ているな」",
        "imageId": 94003905,
        "type": 15,
        "dropPriority": 2005
    },
    {
        "id": 94003906,
        "name": "功徳の玉",
        "detail": "【イベントアイテム／クエスト実行アイテム】\n『星の三蔵ちゃん、天竺に行く』で手に入れた\nあらゆる可能性秘める輝く玉。\n\n「ぎゃてぇ、掴みやすいカタチなのが最高ね！」",
        "imageId": 94003906,
        "type": 15,
        "dropPriority": 2006
    },
    {
        "id": 94004501,
        "name": "勇気のきびだんご",
        "detail": "【イベントアイテム／BP回復アイテム】\n『天魔御伽草子 鬼ヶ島』で手に入れた\nおばあさんの愛情溢れるきびだんご。\n\n『天魔御伽草子 鬼ヶ島』の討伐戦において\nBPを2回復する。",
        "imageId": 94004501,
        "type": 18,
        "dropPriority": 94013502
    },
    {
        "id": 94004502,
        "name": "ゴールデンきびだんご",
        "detail": "【イベントアイテム／BP回復アイテム】\n『天魔御伽草子 鬼ヶ島』で手に入れた\nゴールデンなきびだんご。\nパイン味。\n\n『天魔御伽草子 鬼ヶ島』の討伐戦において\nBPを8回復する。",
        "imageId": 94004502,
        "type": 18,
        "dropPriority": 94013501
    },
    {
        "id": 94004503,
        "name": "鬼印のつづら",
        "detail": "【イベントアイテム】\n『天魔御伽草子 鬼ヶ島』で手に入れた\n鬼が人々から奪った金銀財宝が詰まったつづら。",
        "imageId": 94004503,
        "type": 15,
        "dropPriority": 2005
    },
    {
        "id": 94004504,
        "name": "錦の反物",
        "detail": "【イベントアイテム】\n『天魔御伽草子 鬼ヶ島』で手に入れた\n鬼が人々から奪った豪華絢爛な反物。",
        "imageId": 94004504,
        "type": 15,
        "dropPriority": 2004
    },
    {
        "id": 94004505,
        "name": "竜宮珊瑚",
        "detail": "【イベントアイテム】\n『天魔御伽草子 鬼ヶ島』で手に入れた\n鬼が人々から奪った世にも珍しい珊瑚。",
        "imageId": 94004505,
        "type": 15,
        "dropPriority": 2003
    },
    {
        "id": 94004506,
        "name": "迅犬豆",
        "detail": "【イベントアイテム／ブーストアイテム】\n『天魔御伽草子 鬼ヶ島』で手に入れた\n撒けば風を切って\n目にも止まらぬ速さで鬼に当たる豆。\n\n『天魔御伽草子 鬼ヶ島』の討伐戦で使用すると\n味方全体＜控え含む＞のQuickカードの性能が\n50%アップする。",
        "imageId": 94004506,
        "type": 19,
        "dropPriority": 4008
    },
    {
        "id": 94004507,
        "name": "賢猿豆",
        "detail": "【イベントアイテム／ブーストアイテム】\n『天魔御伽草子 鬼ヶ島』で手に入れた\n撒けば自在に宙を舞い\n追いかけるように鬼に当たる豆。\n\n『天魔御伽草子 鬼ヶ島』の討伐戦で使用すると\n味方全体＜控え含む＞のArtsカードの性能が\n50%アップする。",
        "imageId": 94004507,
        "type": 19,
        "dropPriority": 4007
    },
    {
        "id": 94004508,
        "name": "剛雉豆",
        "detail": "【イベントアイテム／ブーストアイテム】\n『天魔御伽草子 鬼ヶ島』で手に入れた\n撒けば虚空を貫き\n岩をも砕く勢いで鬼に当たる豆。\n\n『天魔御伽草子 鬼ヶ島』の討伐戦で使用すると\n味方全体＜控え含む＞のBusterカードの性能が\n50%アップする。",
        "imageId": 94004508,
        "type": 19,
        "dropPriority": 4006
    },
    {
        "id": 94004509,
        "name": "ゴールデンベアライター",
        "detail": "【イベントアイテム／霊基再臨素材】\n『天魔御伽草子 鬼ヶ島』で手に入れた\nゴールデンなクマをあしらった\nゴールデンなライター。",
        "imageId": 94004509,
        "type": 15,
        "dropPriority": 2009
    },
    {
        "id": 94005601,
        "name": "真水",
        "detail": "【イベントアイテム】\n『夏だ！ 海だ！ 開拓だ！ FGO 2016 Summer』\nで手に入れた資源。\n\n生物が生きていくには欠かせない。\n無人島では塩水はいくらでも手に入るが、\n真水は貴重品となる。\n\n「美味しいんだぜ！　ゴクゴク飲みたいぜ！」\n「ダメですよ凶犬騎士」",
        "imageId": 94005601,
        "type": 15,
        "dropPriority": 2002
    },
    {
        "id": 94005602,
        "name": "食料",
        "detail": "【イベントアイテム】\n『夏だ！ 海だ！ 開拓だ！ FGO 2016 Summer』\nで手に入れた資源。\n\n無人島で採れる食料は多種多様。\n新鮮な木の実に、大きな魚、怪しいキノコ。\n好き嫌いなんて言っていられない！\n\n「毒キノコの見分け方？　そんなの食べれば分かんだろ」\n「ははあ。舌先に乗せて三秒ルールでござるな？」",
        "imageId": 94005602,
        "type": 15,
        "dropPriority": 2001
    },
    {
        "id": 94005603,
        "name": "木材",
        "detail": "【イベントアイテム】\n『夏だ！ 海だ！ 開拓だ！ FGO 2016 Summer』\nで手に入れた資源。\n\nジャングルで簡単に手に入る木材は\n加工が簡単で、サバイバル初心者にはもってこい。\n伐採し過ぎに注意！\n\n「この堅さ……どこから見てもマルタ殿……ッ！」\n「よし。新しいサンドバッグを見つけたわ」",
        "imageId": 94005603,
        "type": 15,
        "dropPriority": 2005
    },
    {
        "id": 94005604,
        "name": "石材",
        "detail": "【イベントアイテム】\n『夏だ！ 海だ！ 開拓だ！ FGO 2016 Summer』\nで手に入れた資源。\n\n岸壁などでいくらでも手に入る石材は\n重くて加工が大変だけど\nその分風雨に負けない頑丈な建物を作れるぞ！\n\n「暇だったので、ちょうどいい形に削っておいたのだ」\n「師匠、こういう力技の工作、得意だよな……」",
        "imageId": 94005604,
        "type": 15,
        "dropPriority": 2004
    },
    {
        "id": 94005605,
        "name": "鉄材",
        "detail": "【イベントアイテム】\n『夏だ！ 海だ！ 開拓だ！ FGO 2016 Summer』\nで手に入れた資源。\n\n溶かして自由な形に加工できる鉄材は\n創作欲を刺激してやまない。\n便利なものをどんどん作ろう！\n\n「鐘でよければ私が鋳型を作りますが……」\n「物騒なのでおやめになってくださいましね？」",
        "imageId": 94005605,
        "type": 15,
        "dropPriority": 2003
    },
    {
        "id": 94005606,
        "name": "鈴鳴りの枝",
        "detail": "【イベントアイテム／霊基再臨素材】\n『夏だ！ 海だ！ 開拓だ！ FGO 2016 Summer』\nで手に入れた\n濃縮されたマナが宿った世界樹の枝。\n振ると鈴のような不思議な音色がする。",
        "imageId": 94005606,
        "type": 15,
        "dropPriority": 2006
    },
    {
        "id": 94006101,
        "name": "オイル",
        "detail": "【イベントアイテム】\n『夏だ！ 海だ！ 開拓だ！ FGO 2016 Summer』\nで手に入れた資源。\n\n機械を動かすには欠かせない。\n割れた大地のあちこちから湧き出ているが\n動力として使うには精製が必要。",
        "imageId": 94006101,
        "type": 15,
        "dropPriority": 2002
    },
    {
        "id": 94006102,
        "name": "セメント",
        "detail": "【イベントアイテム】\n『夏だ！ 海だ！ 開拓だ！ FGO 2016 Summer』\nで手に入れた資源。\n\n近代的な建築のまさに礎。\n砂と砂利と水を混ぜて、捏ねて、乾かせば\n頑丈なコンクリートになる。",
        "imageId": 94006102,
        "type": 15,
        "dropPriority": 2001
    },
    {
        "id": 94006103,
        "name": "レアルタ合金",
        "detail": "【イベントアイテム】\n『夏だ！ 海だ！ 開拓だ！ FGO 2016 Summer』\nで手に入れた資源。\n\n失われた文明によって造られた合金。\n強固かつしなやかで粘りがあり\n支柱や鉄筋に使えば、超高層の建造物も\nプラモデルのようにたやすく建築できる。",
        "imageId": 94006103,
        "type": 15,
        "dropPriority": 2005
    },
    {
        "id": 94006104,
        "name": "エードラム合金",
        "detail": "【イベントアイテム】\n『夏だ！ 海だ！ 開拓だ！ FGO 2016 Summer』\nで手に入れた資源。\n\n失われた文明によって造られた合金。\n加工が簡単で、エネルギーの伝導率が高く\n機械部品の製造に適している。",
        "imageId": 94006104,
        "type": 15,
        "dropPriority": 2004
    },
    {
        "id": 94006105,
        "name": "イシュカ合金",
        "detail": "【イベントアイテム】\n『夏だ！ 海だ！ 開拓だ！ FGO 2016 Summer』\nで手に入れた資源。\n\n失われた文明によって造られた合金。\n軽量でありながら耐久性に優れ\n高熱でも変形しない夢の超金属。\n希少かつ加工は困難だが、\nこの金属を使えばどんな不可能も可能になる。",
        "imageId": 94006105,
        "type": 15,
        "dropPriority": 2003
    },
    {
        "id": 94006106,
        "name": "複製ゲイ・ボルク",
        "detail": "【イベントアイテム】\n『夏だ！ 海だ！ 開拓だ！ FGO 2016 Summer』\nで手に入れた\nスカサハがトネリコの枝を加工して製作した\nゲイ・ボルクの複製品。",
        "imageId": 94006106,
        "type": 15,
        "dropPriority": 2006
    },
    {
        "id": 94006401,
        "name": "高級プリン",
        "detail": "【イベントアイテム】\n『魔法少女紀行 ～プリズマ・コーズ～』\nで手に入れた値段が高めのプリン。\nデリシャス。",
        "imageId": 94006401,
        "type": 15,
        "dropPriority": 2001
    },
    {
        "id": 94006402,
        "name": "マジカル☆ブシドームサシ",
        "detail": "【イベントアイテム】\n『魔法少女紀行 ～プリズマ・コーズ～』\nで手に入れたアニメのDVD。\n「相対的な善と悪」を軸とした厚みのある\nストーリーが大きなお友達にも高評価。",
        "imageId": 94006402,
        "type": 15,
        "dropPriority": 2002
    },
    {
        "id": 94006403,
        "name": "ライオン号くん",
        "detail": "【イベントアイテム】\n『魔法少女紀行 ～プリズマ・コーズ～』\nで手に入れた玩具。\n推進能力があり、お風呂等で遊ぶ事ができる。",
        "imageId": 94006403,
        "type": 15,
        "dropPriority": 2003
    },
    {
        "id": 94006404,
        "name": "ハートのブレスレット",
        "detail": "【イベントアイテム／霊基再臨素材】\n『魔法少女紀行 ～プリズマ・コーズ～』\nで手に入れたブレスレット。\nハートのチャームがアクセント。",
        "imageId": 94006404,
        "type": 15,
        "dropPriority": 2004
    },
    {
        "id": 94007101,
        "name": "ネロメダル〔銅〕",
        "detail": "【イベントアイテム】\n『ネロ祭再び ～2016 Autumn～』で手に入れた、\n参加者に褒章として与えられる銅のメダル。",
        "imageId": 94000301,
        "type": 15,
        "dropPriority": 2001
    },
    {
        "id": 94007102,
        "name": "ネロメダル〔銀〕",
        "detail": "【イベントアイテム】\n『ネロ祭再び ～2016 Autumn～』で手に入れた、\n勇気ある者に褒章として与えられる銀のメダル。",
        "imageId": 94000302,
        "type": 15,
        "dropPriority": 2002
    },
    {
        "id": 94007103,
        "name": "ネロメダル〔金〕",
        "detail": "【イベントアイテム】\n『ネロ祭再び ～2016 Autumn～』で手に入れた、\n力ある者に褒章として与えられる金のメダル。",
        "imageId": 94000303,
        "type": 15,
        "dropPriority": 2003
    },
    {
        "id": 94007104,
        "name": "真紅の花びら",
        "detail": "【イベントアイテム】\n『ネロ祭再び ～2016 Autumn～』で手に入れた、\nネロ・クラウディウス皇帝を讃える薔薇の花びら。",
        "imageId": 94007104,
        "type": 15,
        "dropPriority": 2004
    },
    {
        "id": 94007401,
        "name": "プチケーキ",
        "detail": "【イベントアイテム】\n『復刻：歌うカボチャ城の冒険～\nマッドパーティー2015～ ライト版』で手に入れた\nちいさなカップケーキ。",
        "imageId": 94000501,
        "type": 15,
        "dropPriority": 2001
    },
    {
        "id": 94007402,
        "name": "スイートキャンドル",
        "detail": "【イベントアイテム】\n『復刻：歌うカボチャ城の冒険～\nマッドパーティー2015～ ライト版』で手に入れた\n艶やかな光を放つキャンドル。",
        "imageId": 94000502,
        "type": 15,
        "dropPriority": 2003
    },
    {
        "id": 94007403,
        "name": "いたずらコウモリ",
        "detail": "【イベントアイテム】\n『復刻：歌うカボチャ城の冒険～\nマッドパーティー2015～ ライト版』で手に入れた\nかわいいコウモリの飾りもの。",
        "imageId": 94000503,
        "type": 15,
        "dropPriority": 2002
    },
    {
        "id": 94007404,
        "name": "かぼちゃランタン",
        "detail": "【イベントアイテム】\n『復刻：歌うカボチャ城の冒険～\nマッドパーティー2015～ ライト版』で手に入れた\nとぼけたカボチャの置きもの。",
        "imageId": 94000504,
        "type": 15,
        "dropPriority": 2004
    },
    {
        "id": 94007701,
        "name": "銅のズダ袋",
        "detail": "【イベントアイテム】\n『ハロウィン・カムバック！ 超極☆大かぼちゃ村 \n～そして冒険へ……～』で手に入れた、\n銅貨がぱんぱんに詰まった袋。\n\n長い旅には路銀が必要。\nお金が無ければ宿屋にも泊まれないのだ。",
        "imageId": 94007701,
        "type": 15,
        "dropPriority": 2001
    },
    {
        "id": 94007702,
        "name": "銀のズダ袋",
        "detail": "【イベントアイテム】\n『ハロウィン・カムバック！ 超極☆大かぼちゃ村\n～そして冒険へ……～』で手に入れた、 \n銀貨がぱんぱんに詰まった袋。 \n\n冒険には装備が必要。\n武器屋や道具屋で装備を整えよう。",
        "imageId": 94007702,
        "type": 15,
        "dropPriority": 2002
    },
    {
        "id": 94007703,
        "name": "金のズダ袋",
        "detail": "【イベントアイテム】\n『ハロウィン・カムバック！ 超極☆大かぼちゃ村 \n～そして冒険へ……～』で手に入れた、\n金貨がぱんぱんに詰まった袋。\n\n良い装備は値段も高い。\n勇者たるものケチらず一番高い装備を買いしめるべし！",
        "imageId": 94007703,
        "type": 15,
        "dropPriority": 2003
    },
    {
        "id": 94007704,
        "name": "竜のオーブ",
        "detail": "【イベントアイテム／霊基再臨素材】\n『ハロウィン・カムバック！ 超極☆大かぼちゃ村 \n～そして冒険へ……～』で手に入れた、\n竜の力を宿した宝玉。\n\n勇気に共鳴し、勇者エリドラムの秘めたる力を引き出す。\nエリドラムが冒険者登録名である事を、エリザベートはまだ知らない……。",
        "imageId": 94007704,
        "type": 15,
        "dropPriority": 2010
    },
    {
        "id": 94007705,
        "name": "勇者の剣",
        "detail": "【イベントアイテム／ブーストアイテム】\n『ハロウィン・カムバック！ 超極☆大かぼちゃ村 \n～そして冒険へ……～』で手に入れた、\n勇者が持つに相応しい煌びやかな剣。\nその名はエイティーン。\n\n超極☆大かぼちゃ村のクエストで使用すると、\n味方全体(控え含む)のBusterカード性能が50%アップする。",
        "imageId": 94007705,
        "type": 19,
        "dropPriority": 4006
    },
    {
        "id": 94007706,
        "name": "勇者の槍",
        "detail": "【イベントアイテム／ブーストアイテム】\n『ハロウィン・カムバック！ 超極☆大かぼちゃ村 \n～そして冒険へ……～』で手に入れた、\n勇者が持つに相応しい艶やかな槍。\nその名はバブルエイジ。\n\n超極☆大かぼちゃ村のクエストで使用すると、\n味方全体(控え含む)のQuickカード性能が50%アップする。",
        "imageId": 94007706,
        "type": 19,
        "dropPriority": 4005
    },
    {
        "id": 94007707,
        "name": "勇者の弓",
        "detail": "【イベントアイテム／ブーストアイテム】\n『ハロウィン・カムバック！ 超極☆大かぼちゃ村 \n～そして冒険へ……～』で手に入れた、\n勇者が持つに相応しい華やかな弓。\nその名はワンメガショック。\n\n超極☆大かぼちゃ村のクエストで使用すると、\n味方全体(控え含む)のArtsカード性能が50%アップする。",
        "imageId": 94007707,
        "type": 19,
        "dropPriority": 4004
    },
    {
        "id": 94007708,
        "name": "勇者の盾",
        "detail": "【イベントアイテム／ブーストアイテム】\n『ハロウィン・カムバック！ 超極☆大かぼちゃ村 \n～そして冒険へ……～』で手に入れた、\n勇者の身を守るに相応しい豪華絢爛な盾。\nその名はレトロニア。\n\n超極☆大かぼちゃ村のクエストで使用すると、\n味方全体(控え含む)に無敵状態(3回)が付与される。",
        "imageId": 94007708,
        "type": 19,
        "dropPriority": 4008
    },
    {
        "id": 94007709,
        "name": "勇者のマント",
        "detail": "【イベントアイテム／ブーストアイテム】\n『ハロウィン・カムバック！ 超極☆大かぼちゃ村 \n～そして冒険へ……～』で手に入れた、\n勇者が身に着けるに相応しい勇壮美麗なマント。\nその名はスタジャーン。\n\n超極☆大かぼちゃ村のクエストで使用すると、\n味方全体(控え含む)の宝具威力が50%アップする。",
        "imageId": 94007709,
        "type": 19,
        "dropPriority": 4009
    },
    {
        "id": 94008301,
        "name": "EXTELLAチケット",
        "detail": "【イベント交換アイテム】\nFate新作アクション！\n 『Fate/EXTELLA(フェイト／エクステラ) 』の\n発売を記念して配布された交換チケット。\n(交換はダ・ヴィンチ工房にて2016/11/16 13:59まで)",
        "imageId": 94008301,
        "type": 15,
        "dropPriority": 2001
    },
    {
        "id": 94008701,
        "name": "ミニリボン",
        "detail": "【イベントアイテム】\n『復刻：ほぼ週間 サンタオルタさん ライト版』\nで手に入れたクリスマスツリーを\n彩るかわいいリボン。",
        "imageId": 94001201,
        "type": 15,
        "dropPriority": 2001
    },
    {
        "id": 94008702,
        "name": "シルバーベル",
        "detail": "【イベントアイテム】\n『復刻：ほぼ週間 サンタオルタさん ライト版』\nで手に入れたクリスマスツリーに\n吊るす聖なるベル。",
        "imageId": 94001202,
        "type": 15,
        "dropPriority": 2002
    },
    {
        "id": 94008703,
        "name": "ゴールドスター",
        "detail": "【イベントアイテム】\n『復刻：ほぼ週間 サンタオルタさん ライト版』\nで手に入れたクリスマスツリーの\nてっぺんに輝く星。",
        "imageId": 94001203,
        "type": 15,
        "dropPriority": 2003
    },
    {
        "id": 94008704,
        "name": "魔法のくつした",
        "detail": "【イベントアイテム】\n『復刻：ほぼ週間 サンタオルタさん ライト版』\nで手に入れたこどもたちの\n願いの詰まったくつした。",
        "imageId": 94001204,
        "type": 15,
        "dropPriority": 2004
    },
    {
        "id": 94008705,
        "name": "特別引換券",
        "detail": "【イベントアイテム】\n『復刻：ほぼ週間 サンタオルタさん ライト版』\nで手に入れたごほうびとして\n与えられる謎のチケット。",
        "imageId": 94001206,
        "type": 15,
        "dropPriority": 2005
    },
    {
        "id": 94009001,
        "name": "フルーツケーキ",
        "detail": "【イベントアイテム】\n『二代目はオルタちゃん ～2016クリスマス～』\nで手に入れた、果物をふんだんに使ったケーキ。",
        "imageId": 94009001,
        "type": 15,
        "dropPriority": 2003
    },
    {
        "id": 94009002,
        "name": "ショートケーキ",
        "detail": "【イベントアイテム】\n『二代目はオルタちゃん ～2016クリスマス～』\nで手に入れた、真っ赤なイチゴがキュートなケーキ。",
        "imageId": 94009002,
        "type": 15,
        "dropPriority": 2002
    },
    {
        "id": 94009003,
        "name": "チーズケーキ",
        "detail": "【イベントアイテム】\n『二代目はオルタちゃん ～2016クリスマス～』\nで手に入れた、ふんわりやさしい口あたりのケーキ。",
        "imageId": 94009003,
        "type": 15,
        "dropPriority": 2001
    },
    {
        "id": 94009004,
        "name": "ブッシュ・ド・ノエル",
        "detail": "【イベントアイテム】\n『二代目はオルタちゃん ～2016クリスマス～』\nで手に入れた、丸太のような豪華なケーキ。",
        "imageId": 94009004,
        "type": 15,
        "dropPriority": 2004
    },
    {
        "id": 94009005,
        "name": "奇跡のくつした",
        "detail": "【イベントアイテム】\n『二代目はオルタちゃん ～2016クリスマス～』\nで手に入れた、こどもたちの夢の詰まったくつした。",
        "imageId": 94009005,
        "type": 15,
        "dropPriority": 2005
    },
    {
        "id": 94009006,
        "name": "ジル・ド・レェ人形",
        "detail": "【イベントアイテム／霊基再臨素材】\n『二代目はオルタちゃん ～2016クリスマス～』\nで手に入れた、キモカワイイ？人形。",
        "imageId": 94009006,
        "type": 15,
        "dropPriority": 2006
    },
    {
        "id": 94009007,
        "name": "白銀の交換券",
        "detail": "【イベント交換アイテム】\n『二代目はオルタちゃん ～2016クリスマス～』\nでごほうびとして与えられる謎のチケット。",
        "imageId": 94009007,
        "type": 15,
        "dropPriority": 2007
    },
    {
        "id": 6527,
        "name": "万死の毒針",
        "detail": "【スキル強化＆霊基再臨素材】\nこの針の毒を受けたものはすぐには死ねず\n数多の死を繰り返し体験し\nその魂までも朽ち果てると云う。",
        "imageId": 6527,
        "type": 11,
        "dropPriority": 8188
    },
    {
        "id": 6528,
        "name": "原初の産毛",
        "detail": "【スキル強化＆霊基再臨素材】\n猛々しく燃え盛る炎のような獣の毛。\nその神々しさから、魔除けの御守として珍重される。",
        "imageId": 6528,
        "type": 11,
        "dropPriority": 8291
    },
    {
        "id": 6529,
        "name": "呪獣胆石",
        "detail": "【スキル強化＆霊基再臨素材】\n呪われた獣の体内で呪いが醸成されてできた石。\n晴れることのない強烈な呪いを放ち続ける。",
        "imageId": 6529,
        "type": 11,
        "dropPriority": 8290
    }
]